MyModule/__init__.py
MyModule/bcalc.py
BCalc-1.0.1.dist-info/LICENSE
BCalc-1.0.1.dist-info/METADATA
BCalc-1.0.1.dist-info/WHEEL
BCalc-1.0.1.dist-info/top_level.txt
BCalc-1.0.1.dist-info/zip-safe
BCalc-1.0.1.dist-info/RECORD
