Metadata-Version: 2.1
Name: BCalc
Version: 1.0.1
Summary: A Calculator with many uses
Home-page: https://modules.breezecodes.com
Author: Jace Billingsley
Author-email: jacebphotography@outlook.com
License: MIT
Platform: UNKNOWN
Classifier: Programming Language :: Python :: 3
Classifier: License :: OSI Approved :: MIT License
Classifier: Operating System :: OS Independent
Requires-Python: >=3.0
